<widget type="EpochWidget" label="i18n:epoch-title">

  <description>i18n:epoch-description</description>

  <metadata>
    <size width="40" height="40" type="fixed"/>
    <property frame="RoundedBox" visible="Never" visual="false" refreshable="false"/>
  </metadata>

  <inputs>

    <param name="$operation" value="EPOCH" setting="false" binding="false" control="false"/>

    <param setting="false" label="i18n:epoch-in" name="$in"/>

  </inputs>

  <outputs>

    <param setting="false" label="i18n:epoch-out" name="$out"/>

  </outputs>

</widget>
